odoo8_addon_account_banking_tests-8.0.0.1.0.99.dev2-py2.7-nspkg.pth
odoo8_addon_account_banking_tests-8.0.0.1.0.99.dev2.dist-info/DESCRIPTION.rst
odoo8_addon_account_banking_tests-8.0.0.1.0.99.dev2.dist-info/METADATA
odoo8_addon_account_banking_tests-8.0.0.1.0.99.dev2.dist-info/RECORD
odoo8_addon_account_banking_tests-8.0.0.1.0.99.dev2.dist-info/WHEEL
odoo8_addon_account_banking_tests-8.0.0.1.0.99.dev2.dist-info/metadata.json
odoo8_addon_account_banking_tests-8.0.0.1.0.99.dev2.dist-info/namespace_packages.txt
odoo8_addon_account_banking_tests-8.0.0.1.0.99.dev2.dist-info/top_level.txt
odoo_addons/account_banking_tests/__init__.py
odoo_addons/account_banking_tests/__openerp__.py
odoo_addons/account_banking_tests/i18n/account_banking_tests.pot
odoo_addons/account_banking_tests/static/description/icon.png
odoo_addons/account_banking_tests/tests/__init__.py
odoo_addons/account_banking_tests/tests/test_payment_roundtrip.py
